multi_rise/.__init__.py.un~
multi_rise/.combine.py.un~
multi_rise/__init__.py
multi_rise/combine.py
multi_rise-0.1.2.dist-info/entry_points.txt
multi_rise-0.1.2.dist-info/WHEEL
multi_rise-0.1.2.dist-info/METADATA
multi_rise-0.1.2.dist-info/RECORD
