Metadata-Version: 1.2
Name: multi_rise
Version: 0.1.2
Summary: This is a quick shortcut to combine Jupyter notebooks into a single rise
Home-page: https://github.com/mpacer/multi_rise
License: UNKNOWN
Author: M Pacer
Author-email: mpacer@berkeley.edu
Requires-Python: >=3.4
Classifier: License :: OSI Approved :: MIT License
Classifier: Programming Language :: Python :: 3
Classifier: Topic :: Documentation
Requires-Dist: nbformat>4
